MANIFEST.in
README.rst
setup.py
aliyun_python_sdk_cspro.egg-info/PKG-INFO
aliyun_python_sdk_cspro.egg-info/SOURCES.txt
aliyun_python_sdk_cspro.egg-info/dependency_links.txt
aliyun_python_sdk_cspro.egg-info/requires.txt
aliyun_python_sdk_cspro.egg-info/top_level.txt
aliyunsdkcspro/__init__.py
aliyunsdkcspro/endpoint.py
aliyunsdkcspro/request/__init__.py
aliyunsdkcspro/request/v20180315/AddOmniSecCheckConfigRequest.py
aliyunsdkcspro/request/v20180315/AddSecCheckSampleLibRequest.py
aliyunsdkcspro/request/v20180315/AddSecCheckSampleRequest.py
aliyunsdkcspro/request/v20180315/AddSiteCheckConfigRequest.py
aliyunsdkcspro/request/v20180315/AuthSecCheckSamplePicUploadRequest.py
aliyunsdkcspro/request/v20180315/DelOmniSecCheckConfigRequest.py
aliyunsdkcspro/request/v20180315/DelSecCheckSampleLibRequest.py
aliyunsdkcspro/request/v20180315/DelSecCheckSampleRequest.py
aliyunsdkcspro/request/v20180315/DelSiteCheckConfigRequest.py
aliyunsdkcspro/request/v20180315/GetIndexBaselineRequest.py
aliyunsdkcspro/request/v20180315/GetIpProfileRequest.py
aliyunsdkcspro/request/v20180315/GetPhoneProfileRequest.py
aliyunsdkcspro/request/v20180315/GetSecCheckResultDetailRequest.py
aliyunsdkcspro/request/v20180315/GetSiteCheckResultDetailRequest.py
aliyunsdkcspro/request/v20180315/GetSnapshotInfoRequest.py
aliyunsdkcspro/request/v20180315/InvokeOmniSecCheckImmediatelyRequest.py
aliyunsdkcspro/request/v20180315/PostPunishOrderRequest.py
aliyunsdkcspro/request/v20180315/QueryPunishOrderListRequest.py
aliyunsdkcspro/request/v20180315/QueryPunishOrderRequest.py
aliyunsdkcspro/request/v20180315/QuerySecCheckConfigsRequest.py
aliyunsdkcspro/request/v20180315/QuerySecCheckLatestSummaryRequest.py
aliyunsdkcspro/request/v20180315/QuerySecCheckResultRequest.py
aliyunsdkcspro/request/v20180315/QuerySecCheckSampleLibsRequest.py
aliyunsdkcspro/request/v20180315/QuerySecCheckSamplesRequest.py
aliyunsdkcspro/request/v20180315/QuerySiteCheckConfigsRequest.py
aliyunsdkcspro/request/v20180315/QuerySiteCheckProgressRequest.py
aliyunsdkcspro/request/v20180315/QuerySiteCheckResultRequest.py
aliyunsdkcspro/request/v20180315/RevokePunishOrderRequest.py
aliyunsdkcspro/request/v20180315/SetIndexBaselineRequest.py
